{
  "note-list": [
    {
      "id": 1,
      "title": "Список покупок",
      "text": "Помидоры, огурцы, сигареты, пурген",
      "dateCreate": "Thu Feb 13 2025 14:16:59 GMT+0400 (GMT+04:00)"
    },
    {
      "id": 2,
      "title": "Что бы посмотреть",
      "text": "Груз 200, Сербский фильм, Капитан Марвел",
      "dateCreate": "Thu Feb 13 2025 14:04:25 GMT+0400 (GMT+04:00)"
    },
    {
      "id": 3,
      "title": "Заметка 3",
      "text": "хыххма aaah",
      "dateCreate": "Tue Feb 11 2025 18:45:48 GMT+0400 (GMT+04:00)"
    }
  ]
}